Workbook
Name Cust_ID: customersdata[Cust_ID]
Name hsncode: Products!$D$11:$D$20
Name Slicer_Name: #N/A
Name Slicer_Product_Name: #N/A
Name Slicer_Vendor_Name: #N/A

Sheet Dashboard
O15: Notification!
O18: {=_xlfn._xlws.FILTER(Inventory!K11:K20,Inventory!K11:K20<>"")} -> 📞9812xxxxxx
O19: 📞9812xxxxxx
O20: 📞9812xxxxxx
O21: 📞9813xxxxxx
O22: 📞9813xxxxxx
O23: 📞9813xxxxxx
O24: 📞9813xxxxxx
O25: 📞9814xxxxxx
O26: 📞9814xxxxxx
O27: 📞9814xxxxxx

Sheet Customers
D8: Cust_ID | E8: Name | F8: Email | G8: Adress
D9: 100 | E9: Ram Sales | F9: Ram@gmail.com | G9: Delhi, India
D10: 101 | E10: Atul Ltd | F10: Atulgmail.com | G10: 121102, Palwal, HR
D11: 102 | E11: MK Tech. | F11: MK@gmail.com | G11: Faridabad, 121101
D12: 103 | E12: 99store | F12: 99store@gmail.com | G12: Agra, UP
D13: 104 | E13: Rajesh Kumar | F13: Rajesh@gmail.com | G13: New Delhi, 110011
D14: 105 | E14: Amit | F14: Amit@gmail.com | G14: Gurgao, Sec-15
D15: 106 | E15: Jain Tel. | F15: Jain@gmail.com | G15: Janpath, New Delhi

Sheet Products
D9: HSN Code | E9: Product Name | F9: Cost | G9: Selling Price
D11: N1001 | E11: Smart Watch | F11: 980 | G11: 1176
D12: N1002 | E12: Laptop HP xyz i5 | F12: 34500 | G12: 41400
D13: N1003 | E13: Wireless Printer | F13: 4600 | G13: 5520
D14: N1004 | E14: Desktop | F14: 21000 | G14: 25200
D15: N1005 | E15: Mouse | F15: 200 | G15: 240
D16: N1006 | E16: Rgb Keyboard | F16: 340 | G16: 408
D17: N1007 | E17: Camera | F17: 52000 | G17: 62400
D18: N1008 | E18: HeadPhones | F18: 799 | G18: 958.8
D19: N1009 | E19: Speakers | F19: 670 | G19: 804
D20: N1010 | E20: Tablets | F20: 23500 | G20: 28200

Sheet Vendors
D9: HSN Code | E9: Product Name | F9: Vendor Name | G9: Phone | H9: Address
D11: N1001 | E11: Smart Watch | F11: Tech99 | G11: 📞9812xxxxxx | H11: Faridabad, 121101
D12: N1002 | E12: Laptop HP xyz i5 | F12: Tech99 | G12: 📞9812xxxxxx | H12: Faridabad, 121102
D13: N1003 | E13: Wireless Printer | F13: Tech99 | G13: 📞9812xxxxxx | H13: Faridabad, 121103
D14: N1004 | E14: Desktop | F14: GG Traders | G14: 📞9813xxxxxx | H14: Gurgaon, Sec-15
D15: N1005 | E15: Mouse | F15: GG Traders | G15: 📞9813xxxxxx | H15: Gurgaon, Sec-16
D16: N1006 | E16: Rgb Keyboard | F16: GG Traders | G16: 📞9813xxxxxx | H16: Gurgaon, Sec-17
D17: N1007 | E17: Camera | F17: GG Traders | G17: 📞9813xxxxxx | H17: Gurgaon, Sec-18
D18: N1008 | E18: HeadPhones | F18: Compac | G18: 📞9814xxxxxx | H18: New Delhi, 110012
D19: N1009 | E19: Speakers | F19: Compac | G19: 📞9814xxxxxx | H19: New Delhi, 110013
D20: N1010 | E20: Tablets | F20: Compac | G20: 📞9814xxxxxx | H20: New Delhi, 110014

Sheet NewEntry
F9: Purchase Entry
F11: Sales Entry

Sheet Purchase
D9: HSN Code | E9: Product Name | F9: Vendor | G9: Date | H9: Units | I9: Cost | J9: Amount
E10: =IFERROR(VLOOKUP(purchasedata[[#This Row],[HSN Code]],productsdata[#All],2,0),"") | F10: =IFERROR(VLOOKUP(purchasedata[[#This Row],[HSN Code]],vendorsdata[#All],3,0),"") | I10: =IFERROR(VLOOKUP(purchasedata[[#This Row],[HSN Code]],productsdata[#All],3,0),"") | J10: =IFERROR(purchasedata[[#This Row],[Units]]*purchasedata[[#This Row],[Cost]],"")
D11: N1001 | E11: =IFERROR(VLOOKUP(purchasedata[[#This Row],[HSN Code]],productsdata[#All],2,0),"") -> Smart Watch | F11: =IFERROR(VLOOKUP(purchasedata[[#This Row],[HSN Code]],vendorsdata[#All],3,0),"") -> Tech99 | G11: 46023 | H11: 12 | I11: =IFERROR(VLOOKUP(purchasedata[[#This Row],[HSN Code]],productsdata[#All],3,0),"") -> 980 | J11: =IFERROR(purchasedata[[#This Row],[Units]]*purchasedata[[#This Row],[Cost]],"") -> 11760
D12: N1002 | E12: =IFERROR(VLOOKUP(purchasedata[[#This Row],[HSN Code]],productsdata[#All],2,0),"") -> Laptop HP xyz i5 | F12: =IFERROR(VLOOKUP(purchasedata[[#This Row],[HSN Code]],vendorsdata[#All],3,0),"") -> Tech99 | G12: 46024 | H12: 1 | I12: =IFERROR(VLOOKUP(purchasedata[[#This Row],[HSN Code]],productsdata[#All],3,0),"") -> 34500 | J12: =IFERROR(purchasedata[[#This Row],[Units]]*purchasedata[[#This Row],[Cost]],"") -> 34500
D13: N1003 | E13: =IFERROR(VLOOKUP(purchasedata[[#This Row],[HSN Code]],productsdata[#All],2,0),"") -> Wireless Printer | F13: =IFERROR(VLOOKUP(purchasedata[[#This Row],[HSN Code]],vendorsdata[#All],3,0),"") -> Tech99 | G13: 46025 | H13: 3 | I13: =IFERROR(VLOOKUP(purchasedata[[#This Row],[HSN Code]],productsdata[#All],3,0),"") -> 4600 | J13: =IFERROR(purchasedata[[#This Row],[Units]]*purchasedata[[#This Row],[Cost]],"") -> 13800
D14: N1004 | E14: =IFERROR(VLOOKUP(purchasedata[[#This Row],[HSN Code]],productsdata[#All],2,0),"") -> Desktop | F14: =IFERROR(VLOOKUP(purchasedata[[#This Row],[HSN Code]],vendorsdata[#All],3,0),"") -> GG Traders | G14: 46026 | H14: 8 | I14: =IFERROR(VLOOKUP(purchasedata[[#This Row],[HSN Code]],productsdata[#All],3,0),"") -> 21000 | J14: =IFERROR(purchasedata[[#This Row],[Units]]*purchasedata[[#This Row],[Cost]],"") -> 168000
D15: N1005 | E15: =IFERROR(VLOOKUP(purchasedata[[#This Row],[HSN Code]],productsdata[#All],2,0),"") -> Mouse | F15: =IFERROR(VLOOKUP(purchasedata[[#This Row],[HSN Code]],vendorsdata[#All],3,0),"") -> GG Traders | G15: 46027 | H15: 4 | I15: =IFERROR(VLOOKUP(purchasedata[[#This Row],[HSN Code]],productsdata[#All],3,0),"") -> 200 | J15: =IFERROR(purchasedata[[#This Row],[Units]]*purchasedata[[#This Row],[Cost]],"") -> 800
D16: N1006 | E16: =IFERROR(VLOOKUP(purchasedata[[#This Row],[HSN Code]],productsdata[#All],2,0),"") -> Rgb Keyboard | F16: =IFERROR(VLOOKUP(purchasedata[[#This Row],[HSN Code]],vendorsdata[#All],3,0),"") -> GG Traders | G16: 46028 | H16: 10 | I16: =IFERROR(VLOOKUP(purchasedata[[#This Row],[HSN Code]],productsdata[#All],3,0),"") -> 340 | J16: =IFERROR(purchasedata[[#This Row],[Units]]*purchasedata[[#This Row],[Cost]],"") -> 3400
D17: N1007 | E17: =IFERROR(VLOOKUP(purchasedata[[#This Row],[HSN Code]],productsdata[#All],2,0),"") -> Camera | F17: =IFERROR(VLOOKUP(purchasedata[[#This Row],[HSN Code]],vendorsdata[#All],3,0),"") -> GG Traders | G17: 46029 | H17: 8 | I17: =IFERROR(VLOOKUP(purchasedata[[#This Row],[HSN Code]],productsdata[#All],3,0),"") -> 52000 | J17: =IFERROR(purchasedata[[#This Row],[Units]]*purchasedata[[#This Row],[Cost]],"") -> 416000
D18: N1008 | E18: =IFERROR(VLOOKUP(purchasedata[[#This Row],[HSN Code]],productsdata[#All],2,0),"") -> HeadPhones | F18: =IFERROR(VLOOKUP(purchasedata[[#This Row],[HSN Code]],vendorsdata[#All],3,0),"") -> Compac | G18: 46030 | H18: 12 | I18: =IFERROR(VLOOKUP(purchasedata[[#This Row],[HSN Code]],productsdata[#All],3,0),"") -> 799 | J18: =IFERROR(purchasedata[[#This Row],[Units]]*purchasedata[[#This Row],[Cost]],"") -> 9588
D19: N1009 | E19: =IFERROR(VLOOKUP(purchasedata[[#This Row],[HSN Code]],productsdata[#All],2,0),"") -> Speakers | F19: =IFERROR(VLOOKUP(purchasedata[[#This Row],[HSN Code]],vendorsdata[#All],3,0),"") -> Compac | G19: 46031 | H19: 10 | I19: =IFERROR(VLOOKUP(purchasedata[[#This Row],[HSN Code]],productsdata[#All],3,0),"") -> 670 | J19: =IFERROR(purchasedata[[#This Row],[Units]]*purchasedata[[#This Row],[Cost]],"") -> 6700
D20: N1010 | E20: =IFERROR(VLOOKUP(purchasedata[[#This Row],[HSN Code]],productsdata[#All],2,0),"") -> Tablets | F20: =IFERROR(VLOOKUP(purchasedata[[#This Row],[HSN Code]],vendorsdata[#All],3,0),"") -> Compac | G20: 46032 | H20: 2 | I20: =IFERROR(VLOOKUP(purchasedata[[#This Row],[HSN Code]],productsdata[#All],3,0),"") -> 23500 | J20: =IFERROR(purchasedata[[#This Row],[Units]]*purchasedata[[#This Row],[Cost]],"") -> 47000
D21: N1003 | E21: =IFERROR(VLOOKUP(purchasedata[[#This Row],[HSN Code]],productsdata[#All],2,0),"") -> Wireless Printer | F21: =IFERROR(VLOOKUP(purchasedata[[#This Row],[HSN Code]],vendorsdata[#All],3,0),"") -> Tech99 | G21: 46033 | H21: 1 | I21: =IFERROR(VLOOKUP(purchasedata[[#This Row],[HSN Code]],productsdata[#All],3,0),"") -> 4600 | J21: =IFERROR(purchasedata[[#This Row],[Units]]*purchasedata[[#This Row],[Cost]],"") -> 4600
D22: N1004 | E22: =IFERROR(VLOOKUP(purchasedata[[#This Row],[HSN Code]],productsdata[#All],2,0),"") -> Desktop | F22: =IFERROR(VLOOKUP(purchasedata[[#This Row],[HSN Code]],vendorsdata[#All],3,0),"") -> GG Traders | G22: 46034 | H22: 2 | I22: =IFERROR(VLOOKUP(purchasedata[[#This Row],[HSN Code]],productsdata[#All],3,0),"") -> 21000 | J22: =IFERROR(purchasedata[[#This Row],[Units]]*purchasedata[[#This Row],[Cost]],"") -> 42000
... D24: N1001 | E24: =IFERROR(VLOOKUP(purchasedata[[#This Row],[HSN Code]],productsdata[#All],2,0),"") -> Smart Watch | F24: =IFERROR(VLOOKUP(purchasedata[[#This Row],[HSN Code]],vendorsdata[#All],3,0),"") -> Tech99 | G24: 46036 | H24: 6 | I24: =IFERROR(VLOOKUP(purchasedata[[#This Row],[HSN Code]],productsdata[#All],3,0),"") -> 980 | J24: =IFERROR(purchasedata[[#This Row],[Units]]*purchasedata[[#This Row],[Cost]],"") -> 5880

Sheet Sales
D9: Cust_ID | E9: Cust_Name | F9: HSN Code | G9: Product Name | H9: Date | I9: Stocks(Units) | J9: Units | K9: Price | L9: Amount
E10: =IFERROR(VLOOKUP(salesdata[[#This Row],[Cust_ID]],customersdata[#All],2,0),"") | G10: =IFERROR(VLOOKUP(salesdata[[#This Row],[HSN Code]],productsdata[#All],2,0),"") | I10: =IFERROR(VLOOKUP(salesdata[[#This Row],[HSN Code]],inventorydata[#All],6,0),"") | K10: =IFERROR(VLOOKUP(salesdata[[#This Row],[HSN Code]],productsdata[#All],4,0),"") | L10: =IFERROR(salesdata[[#This Row],[Units]]*salesdata[[#This Row],[Price]],"")
D11: 100 | E11: =IFERROR(VLOOKUP(salesdata[[#This Row],[Cust_ID]],customersdata[#All],2,0),"") -> Ram Sales | F11: N1001 | G11: =IFERROR(VLOOKUP(salesdata[[#This Row],[HSN Code]],productsdata[#All],2,0),"") -> Smart Watch | H11: 46023 | I11: =IFERROR(VLOOKUP(salesdata[[#This Row],[HSN Code]],inventorydata[#All],6,0),"") -> 10 | J11: 2 | K11: =IFERROR(VLOOKUP(salesdata[[#This Row],[HSN Code]],productsdata[#All],4,0),"") -> 1176 | L11: =IFERROR(salesdata[[#This Row],[Units]]*salesdata[[#This Row],[Price]],"") -> 2352
D12: 101 | E12: =IFERROR(VLOOKUP(salesdata[[#This Row],[Cust_ID]],customersdata[#All],2,0),"") -> Atul Ltd | F12: N1002 | G12: =IFERROR(VLOOKUP(salesdata[[#This Row],[HSN Code]],productsdata[#All],2,0),"") -> Laptop HP xyz i5 | H12: 46024 | I12: =IFERROR(VLOOKUP(salesdata[[#This Row],[HSN Code]],inventorydata[#All],6,0),"") -> 1 | J12: 0 | K12: =IFERROR(VLOOKUP(salesdata[[#This Row],[HSN Code]],productsdata[#All],4,0),"") -> 41400 | L12: =IFERROR(salesdata[[#This Row],[Units]]*salesdata[[#This Row],[Price]],"") -> 0
D13: 102 | E13: =IFERROR(VLOOKUP(salesdata[[#This Row],[Cust_ID]],customersdata[#All],2,0),"") -> MK Tech. | F13: N1003 | G13: =IFERROR(VLOOKUP(salesdata[[#This Row],[HSN Code]],productsdata[#All],2,0),"") -> Wireless Printer | H13: 46025 | I13: =IFERROR(VLOOKUP(salesdata[[#This Row],[HSN Code]],inventorydata[#All],6,0),"") -> 1 | J13: 3 | K13: =IFERROR(VLOOKUP(salesdata[[#This Row],[HSN Code]],productsdata[#All],4,0),"") -> 5520 | L13: =IFERROR(salesdata[[#This Row],[Units]]*salesdata[[#This Row],[Price]],"") -> 16560
D14: 103 | E14: =IFERROR(VLOOKUP(salesdata[[#This Row],[Cust_ID]],customersdata[#All],2,0),"") -> 99store | F14: N1004 | G14: =IFERROR(VLOOKUP(salesdata[[#This Row],[HSN Code]],productsdata[#All],2,0),"") -> Desktop | H14: 46026 | I14: =IFERROR(VLOOKUP(salesdata[[#This Row],[HSN Code]],inventorydata[#All],6,0),"") -> 4 | J14: 6 | K14: =IFERROR(VLOOKUP(salesdata[[#This Row],[HSN Code]],productsdata[#All],4,0),"") -> 25200 | L14: =IFERROR(salesdata[[#This Row],[Units]]*salesdata[[#This Row],[Price]],"") -> 151200
D15: 104 | E15: =IFERROR(VLOOKUP(salesdata[[#This Row],[Cust_ID]],customersdata[#All],2,0),"") -> Rajesh Kumar | F15: N1005 | G15: =IFERROR(VLOOKUP(salesdata[[#This Row],[HSN Code]],productsdata[#All],2,0),"") -> Mouse | H15: 46027 | I15: =IFERROR(VLOOKUP(salesdata[[#This Row],[HSN Code]],inventorydata[#All],6,0),"") -> 2 | J15: 2 | K15: =IFERROR(VLOOKUP(salesdata[[#This Row],[HSN Code]],productsdata[#All],4,0),"") -> 240 | L15: =IFERROR(salesdata[[#This Row],[Units]]*salesdata[[#This Row],[Price]],"") -> 480
D16: 105 | E16: =IFERROR(VLOOKUP(salesdata[[#This Row],[Cust_ID]],customersdata[#All],2,0),"") -> Amit | F16: N1006 | G16: =IFERROR(VLOOKUP(salesdata[[#This Row],[HSN Code]],productsdata[#All],2,0),"") -> Rgb Keyboard | H16: 46028 | I16: =IFERROR(VLOOKUP(salesdata[[#This Row],[HSN Code]],inventorydata[#All],6,0),"") -> 4 | J16: 6 | K16: =IFERROR(VLOOKUP(salesdata[[#This Row],[HSN Code]],productsdata[#All],4,0),"") -> 408 | L16: =IFERROR(salesdata[[#This Row],[Units]]*salesdata[[#This Row],[Price]],"") -> 2448
D17: 106 | E17: =IFERROR(VLOOKUP(salesdata[[#This Row],[Cust_ID]],customersdata[#All],2,0),"") -> Jain Tel. | F17: N1007 | G17: =IFERROR(VLOOKUP(salesdata[[#This Row],[HSN Code]],productsdata[#All],2,0),"") -> Camera | H17: 46029 | I17: =IFERROR(VLOOKUP(salesdata[[#This Row],[HSN Code]],inventorydata[#All],6,0),"") -> 12 | J17: 1 | K17: =IFERROR(VLOOKUP(salesdata[[#This Row],[HSN Code]],productsdata[#All],4,0),"") -> 62400 | L17: =IFERROR(salesdata[[#This Row],[Units]]*salesdata[[#This Row],[Price]],"") -> 62400
E18: =IFERROR(VLOOKUP(salesdata[[#This Row],[Cust_ID]],customersdata[#All],2,0),"") | G18: =IFERROR(VLOOKUP(salesdata[[#This Row],[HSN Code]],productsdata[#All],2,0),"") | I18: =IFERROR(VLOOKUP(salesdata[[#This Row],[HSN Code]],inventorydata[#All],6,0),"") | K18: =IFERROR(VLOOKUP(salesdata[[#This Row],[HSN Code]],productsdata[#All],4,0),"") | L18: =IFERROR(salesdata[[#This Row],[Units]]*salesdata[[#This Row],[Price]],"")
E19: =IFERROR(VLOOKUP(salesdata[[#This Row],[Cust_ID]],customersdata[#All],2,0),"") | G19: =IFERROR(VLOOKUP(salesdata[[#This Row],[HSN Code]],productsdata[#All],2,0),"") | I19: =IFERROR(VLOOKUP(salesdata[[#This Row],[HSN Code]],inventorydata[#All],6,0),"") | K19: =IFERROR(VLOOKUP(salesdata[[#This Row],[HSN Code]],productsdata[#All],4,0),"") | L19: =IFERROR(salesdata[[#This Row],[Units]]*salesdata[[#This Row],[Price]],"")
E20: =IFERROR(VLOOKUP(salesdata[[#This Row],[Cust_ID]],customersdata[#All],2,0),"") | G20: =IFERROR(VLOOKUP(salesdata[[#This Row],[HSN Code]],productsdata[#All],2,0),"") | I20: =IFERROR(VLOOKUP(salesdata[[#This Row],[HSN Code]],inventorydata[#All],6,0),"") | K20: =IFERROR(VLOOKUP(salesdata[[#This Row],[HSN Code]],productsdata[#All],4,0),"") | L20: =IFERROR(salesdata[[#This Row],[Units]]*salesdata[[#This Row],[Price]],"")
E21: =IFERROR(VLOOKUP(salesdata[[#This Row],[Cust_ID]],customersdata[#All],2,0),"") | G21: =IFERROR(VLOOKUP(salesdata[[#This Row],[HSN Code]],productsdata[#All],2,0),"") | I21: =IFERROR(VLOOKUP(salesdata[[#This Row],[HSN Code]],inventorydata[#All],6,0),"") | K21: =IFERROR(VLOOKUP(salesdata[[#This Row],[HSN Code]],productsdata[#All],4,0),"") | L21: =IFERROR(salesdata[[#This Row],[Units]]*salesdata[[#This Row],[Price]],"")
E22: =IFERROR(VLOOKUP(salesdata[[#This Row],[Cust_ID]],customersdata[#All],2,0),"") | G22: =IFERROR(VLOOKUP(salesdata[[#This Row],[HSN Code]],productsdata[#All],2,0),"") | I22: =IFERROR(VLOOKUP(salesdata[[#This Row],[HSN Code]],inventorydata[#All],6,0),"") | K22: =IFERROR(VLOOKUP(salesdata[[#This Row],[HSN Code]],productsdata[#All],4,0),"") | L22: =IFERROR(salesdata[[#This Row],[Units]]*salesdata[[#This Row],[Price]],"")
E23: =IFERROR(VLOOKUP(salesdata[[#This Row],[Cust_ID]],customersdata[#All],2,0),"") | G23: =IFERROR(VLOOKUP(salesdata[[#This Row],[HSN Code]],productsdata[#All],2,0),"") | I23: =IFERROR(VLOOKUP(salesdata[[#This Row],[HSN Code]],inventorydata[#All],6,0),"") | K23: =IFERROR(VLOOKUP(salesdata[[#This Row],[HSN Code]],productsdata[#All],4,0),"") | L23: =IFERROR(salesdata[[#This Row],[Units]]*salesdata[[#This Row],[Price]],"")
E24: =IFERROR(VLOOKUP(salesdata[[#This Row],[Cust_ID]],customersdata[#All],2,0),"") | G24: =IFERROR(VLOOKUP(salesdata[[#This Row],[HSN Code]],productsdata[#All],2,0),"") | I24: =IFERROR(VLOOKUP(salesdata[[#This Row],[HSN Code]],inventorydata[#All],6,0),"") | K24: =IFERROR(VLOOKUP(salesdata[[#This Row],[HSN Code]],productsdata[#All],4,0),"") | L24: =IFERROR(salesdata[[#This Row],[Units]]*salesdata[[#This Row],[Price]],"")
E25: =IFERROR(VLOOKUP(salesdata[[#This Row],[Cust_ID]],customersdata[#All],2,0),"") | G25: =IFERROR(VLOOKUP(salesdata[[#This Row],[HSN Code]],productsdata[#All],2,0),"") | I25: =IFERROR(VLOOKUP(salesdata[[#This Row],[HSN Code]],inventorydata[#All],6,0),"") | K25: =IFERROR(VLOOKUP(salesdata[[#This Row],[HSN Code]],productsdata[#All],4,0),"") | L25: =IFERROR(salesdata[[#This Row],[Units]]*salesdata[[#This Row],[Price]],"")

Sheet Inventory
D9: HSN Code | E9: Product Name | F9: Cost | G9: P Units | H9: S Units | I9: Stock | J9: Stock Amt | K9: Notification | L9: Inventory
F10: =IFERROR(VLOOKUP(purchasedata[[#This Row],[HSN Code]],productsdata[#All],3,0),"") | J10: =IFERROR(inventorydata[[#This Row],[Cost]]*inventorydata[[#This Row],[Stock]],"") | K10: =IFERROR(VLOOKUP(inventorydata[[#This Row],[HSN Code]],vendorsdata[#All],4,0),"")
D11: =IFERROR(purchasedata[[#This Row],[HSN Code]],"") -> N1001 | E11: =IFERROR(purchasedata[[#This Row],[Product Name]],"") -> Smart Watch | F11: =IFERROR(VLOOKUP(purchasedata[[#This Row],[HSN Code]],productsdata[#All],3,0),"") -> 980 | G11: =IFERROR(SUMIF(Purchase!E11:E20,inventorydata[[#This Row],[Product Name]],Purchase!H11:H20),"") -> 12 | H11: =IFERROR(SUMIF(Sales!G11:G17,inventorydata[[#This Row],[Product Name]],Sales!J11:J17),"") -> 2 | I11: =IFERROR(inventorydata[[#This Row],[P Units]]-inventorydata[[#This Row],[S Units]],"") -> 10 | J11: =IFERROR(inventorydata[[#This Row],[Cost]]*inventorydata[[#This Row],[Stock]],"") -> 9800 | K11: =IFERROR(VLOOKUP(inventorydata[[#This Row],[HSN Code]],vendorsdata[#All],4,0),"") -> 📞9812xxxxxx | L11: =IF(inventorydata[[#This Row],[Stock]]>=10,"In Stock","Low Stock") -> In Stock
D12: =IFERROR(purchasedata[[#This Row],[HSN Code]],"") -> N1002 | E12: =IFERROR(purchasedata[[#This Row],[Product Name]],"") -> Laptop HP xyz i5 | F12: =IFERROR(VLOOKUP(purchasedata[[#This Row],[HSN Code]],productsdata[#All],3,0),"") -> 34500 | G12: =IFERROR(SUMIF(Purchase!E12:E21,inventorydata[[#This Row],[Product Name]],Purchase!H12:H21),"") -> 1 | H12: =IFERROR(SUMIF(Sales!G12:G18,inventorydata[[#This Row],[Product Name]],Sales!J12:J18),"") -> 0 | I12: =IFERROR(inventorydata[[#This Row],[P Units]]-inventorydata[[#This Row],[S Units]],"") -> 1 | J12: =IFERROR(inventorydata[[#This Row],[Cost]]*inventorydata[[#This Row],[Stock]],"") -> 34500 | K12: =IFERROR(VLOOKUP(inventorydata[[#This Row],[HSN Code]],vendorsdata[#All],4,0),"") -> 📞9812xxxxxx | L12: =IFERROR(IF(inventorydata[[#This Row],[Stock]]>=10,"In Stock","Low Stock"), " ") -> Low Stock
D13: =IFERROR(purchasedata[[#This Row],[HSN Code]],"") -> N1003 | E13: =IFERROR(purchasedata[[#This Row],[Product Name]],"") -> Wireless Printer | F13: =IFERROR(VLOOKUP(purchasedata[[#This Row],[HSN Code]],productsdata[#All],3,0),"") -> 4600 | G13: =IFERROR(SUMIF(Purchase!E13:E22,inventorydata[[#This Row],[Product Name]],Purchase!H13:H22),"") -> 4 | H13: =IFERROR(SUMIF(Sales!G13:G19,inventorydata[[#This Row],[Product Name]],Sales!J13:J19),"") -> 3 | I13: =IFERROR(inventorydata[[#This Row],[P Units]]-inventorydata[[#This Row],[S Units]],"") -> 1 | J13: =IFERROR(inventorydata[[#This Row],[Cost]]*inventorydata[[#This Row],[Stock]],"") -> 4600 | K13: =IFERROR(VLOOKUP(inventorydata[[#This Row],[HSN Code]],vendorsdata[#All],4,0),"") -> 📞9812xxxxxx | L13: =IFERROR(IF(inventorydata[[#This Row],[Stock]]>=10,"In Stock","Low Stock"), " ") -> Low Stock
D14: =IFERROR(purchasedata[[#This Row],[HSN Code]],"") -> N1004 | E14: =IFERROR(purchasedata[[#This Row],[Product Name]],"") -> Desktop | F14: =IFERROR(VLOOKUP(purchasedata[[#This Row],[HSN Code]],productsdata[#All],3,0),"") -> 21000 | G14: =IFERROR(SUMIF(Purchase!E14:E23,inventorydata[[#This Row],[Product Name]],Purchase!H14:H23),"") -> 10 | H14: =IFERROR(SUMIF(Sales!G14:G20,inventorydata[[#This Row],[Product Name]],Sales!J14:J20),"") -> 6 | I14: =IFERROR(inventorydata[[#This Row],[P Units]]-inventorydata[[#This Row],[S Units]],"") -> 4 | J14: =IFERROR(inventorydata[[#This Row],[Cost]]*inventorydata[[#This Row],[Stock]],"") -> 84000 | K14: =IFERROR(VLOOKUP(inventorydata[[#This Row],[HSN Code]],vendorsdata[#All],4,0),"") -> 📞9813xxxxxx | L14: =IFERROR(IF(inventorydata[[#This Row],[Stock]]>=10,"In Stock","Low Stock"), " ") -> Low Stock
D15: =IFERROR(purchasedata[[#This Row],[HSN Code]],"") -> N1005 | E15: =IFERROR(purchasedata[[#This Row],[Product Name]],"") -> Mouse | F15: =IFERROR(VLOOKUP(purchasedata[[#This Row],[HSN Code]],productsdata[#All],3,0),"") -> 200 | G15: =IFERROR(SUMIF(Purchase!E15:E24,inventorydata[[#This Row],[Product Name]],Purchase!H15:H24),"") -> 4 | H15: =IFERROR(SUMIF(Sales!G15:G21,inventorydata[[#This Row],[Product Name]],Sales!J15:J21),"") -> 2 | I15: =IFERROR(inventorydata[[#This Row],[P Units]]-inventorydata[[#This Row],[S Units]],"") -> 2 | J15: =IFERROR(inventorydata[[#This Row],[Cost]]*inventorydata[[#This Row],[Stock]],"") -> 400 | K15: =IFERROR(VLOOKUP(inventorydata[[#This Row],[HSN Code]],vendorsdata[#All],4,0),"") -> 📞9813xxxxxx | L15: =IFERROR(IF(inventorydata[[#This Row],[Stock]]>=10,"In Stock","Low Stock"), " ") -> Low Stock
D16: =IFERROR(purchasedata[[#This Row],[HSN Code]],"") -> N1006 | E16: =IFERROR(purchasedata[[#This Row],[Product Name]],"") -> Rgb Keyboard | F16: =IFERROR(VLOOKUP(purchasedata[[#This Row],[HSN Code]],productsdata[#All],3,0),"") -> 340 | G16: =IFERROR(SUMIF(Purchase!E16:E25,inventorydata[[#This Row],[Product Name]],Purchase!H16:H25),"") -> 10 | H16: =IFERROR(SUMIF(Sales!G16:G22,inventorydata[[#This Row],[Product Name]],Sales!J16:J22),"") -> 6 | I16: =IFERROR(inventorydata[[#This Row],[P Units]]-inventorydata[[#This Row],[S Units]],"") -> 4 | J16: =IFERROR(inventorydata[[#This Row],[Cost]]*inventorydata[[#This Row],[Stock]],"") -> 1360 | K16: =IFERROR(VLOOKUP(inventorydata[[#This Row],[HSN Code]],vendorsdata[#All],4,0),"") -> 📞9813xxxxxx | L16: =IFERROR(IF(inventorydata[[#This Row],[Stock]]>=10,"In Stock","Low Stock"), " ") -> Low Stock
D17: =IFERROR(purchasedata[[#This Row],[HSN Code]],"") -> N1007 | E17: =IFERROR(purchasedata[[#This Row],[Product Name]],"") -> Camera | F17: =IFERROR(VLOOKUP(purchasedata[[#This Row],[HSN Code]],productsdata[#All],3,0),"") -> 52000 | G17: =IFERROR(SUMIF(Purchase!E17:E26,inventorydata[[#This Row],[Product Name]],Purchase!H17:H26),"") -> 13 | H17: =IFERROR(SUMIF(Sales!G17:G23,inventorydata[[#This Row],[Product Name]],Sales!J17:J23),"") -> 1 | I17: =IFERROR(inventorydata[[#This Row],[P Units]]-inventorydata[[#This Row],[S Units]],"") -> 12 | J17: =IFERROR(inventorydata[[#This Row],[Cost]]*inventorydata[[#This Row],[Stock]],"") -> 624000 | K17: =IFERROR(VLOOKUP(inventorydata[[#This Row],[HSN Code]],vendorsdata[#All],4,0),"") -> 📞9813xxxxxx | L17: =IFERROR(IF(inventorydata[[#This Row],[Stock]]>=10,"In Stock","Low Stock"), " ") -> In Stock
D18: =IFERROR(purchasedata[[#This Row],[HSN Code]],"") -> N1008 | E18: =IFERROR(purchasedata[[#This Row],[Product Name]],"") -> HeadPhones | F18: =IFERROR(VLOOKUP(purchasedata[[#This Row],[HSN Code]],productsdata[#All],3,0),"") -> 799 | G18: =IFERROR(SUMIF(Purchase!E18:E27,inventorydata[[#This Row],[Product Name]],Purchase!H18:H27),"") -> 12 | H18: =IFERROR(SUMIF(Sales!G18:G24,inventorydata[[#This Row],[Product Name]],Sales!J18:J24),"") -> 0 | I18: =IFERROR(inventorydata[[#This Row],[P Units]]-inventorydata[[#This Row],[S Units]],"") -> 12 | J18: =IFERROR(inventorydata[[#This Row],[Cost]]*inventorydata[[#This Row],[Stock]],"") -> 9588 | K18: =IFERROR(VLOOKUP(inventorydata[[#This Row],[HSN Code]],vendorsdata[#All],4,0),"") -> 📞9814xxxxxx | L18: =IFERROR(IF(inventorydata[[#This Row],[Stock]]>=10,"In Stock","Low Stock"), " ") -> In Stock
D19: =IFERROR(purchasedata[[#This Row],[HSN Code]],"") -> N1009 | E19: =IFERROR(purchasedata[[#This Row],[Product Name]],"") -> Speakers | F19: =IFERROR(VLOOKUP(purchasedata[[#This Row],[HSN Code]],productsdata[#All],3,0),"") -> 670 | G19: =IFERROR(SUMIF(Purchase!E19:E28,inventorydata[[#This Row],[Product Name]],Purchase!H19:H28),"") -> 10 | H19: =IFERROR(SUMIF(Sales!G19:G25,inventorydata[[#This Row],[Product Name]],Sales!J19:J25),"") -> 0 | I19: =IFERROR(inventorydata[[#This Row],[P Units]]-inventorydata[[#This Row],[S Units]],"") -> 10 | J19: =IFERROR(inventorydata[[#This Row],[Cost]]*inventorydata[[#This Row],[Stock]],"") -> 6700 | K19: =IFERROR(VLOOKUP(inventorydata[[#This Row],[HSN Code]],vendorsdata[#All],4,0),"") -> 📞9814xxxxxx | L19: =IFERROR(IF(inventorydata[[#This Row],[Stock]]>=10,"In Stock","Low Stock"), " ") -> In Stock
D20: =IFERROR(purchasedata[[#This Row],[HSN Code]],"") -> N1010 | E20: =IFERROR(purchasedata[[#This Row],[Product Name]],"") -> Tablets | F20: =IFERROR(VLOOKUP(purchasedata[[#This Row],[HSN Code]],productsdata[#All],3,0),"") -> 23500 | G20: =IFERROR(SUMIF(Purchase!E20:E29,inventorydata[[#This Row],[Product Name]],Purchase!H20:H29),"") -> 2 | H20: =IFERROR(SUMIF(Sales!G20:G26,inventorydata[[#This Row],[Product Name]],Sales!J20:J26),"") -> 0 | I20: =IFERROR(inventorydata[[#This Row],[P Units]]-inventorydata[[#This Row],[S Units]],"") -> 2 | J20: =IFERROR(inventorydata[[#This Row],[Cost]]*inventorydata[[#This Row],[Stock]],"") -> 47000 | K20: =IFERROR(VLOOKUP(inventorydata[[#This Row],[HSN Code]],vendorsdata[#All],4,0),"") -> 📞9814xxxxxx | L20: =IFERROR(IF(inventorydata[[#This Row],[Stock]]>=10,"In Stock","Low Stock"), " ") -> Low Stock

Sheet Pivots
A2: Count of Name | C2: Customers | G2: Row Labels | H2: Sum of S Units | L2: Row Labels | M2: Sum of Stock
A3: 7 | C3: =GETPIVOTDATA("Name",$A$2) -> 7 | G3: Desktop | H3: 6 | L3: Camera | M3: 12
G4: Rgb Keyboard | H4: 6 | L4: Desktop | M4: 4
G5: Wireless Printer | H5: 3 | L5: HeadPhones | M5: 12
A6: Count of Product Name | C6: Products | G6: Mouse | H6: 2 | L6: Laptop HP xyz i5 | M6: 1
A7: 10 | C7: =GETPIVOTDATA("Product Name",$A$6) -> 10 | G7: Smart Watch | H7: 2 | L7: Mouse | M7: 2
G8: Grand Total | H8: 19 | L8: Rgb Keyboard | M8: 4
L9: Smart Watch | M9: 10
A10: Sum of Amount | C10: Purchase Amt | L10: Speakers | M10: 10
A11: 1024028 | C11: =GETPIVOTDATA("Amount",$A$10) -> 1024028 | L11: Tablets | M11: 2
L12: Wireless Printer | M12: 1
L13: (blank)
A14: Sum of Amount | C14: Sale Amt | L14: Grand Total | M14: 58
A15: 235440 | C15: =GETPIVOTDATA("Amount",$A$14) -> 235440
G16: Row Labels | H16: Sum of Amount
G17: 99store | H17: 151200
A18: Sum of Stock Amt | C18: Stock Amt | G18: Jain Tel. | H18: 62400
A19: 821948 | C19: =GETPIVOTDATA("Stock Amt",$A$18) -> 821948 | G19: MK Tech. | H19: 16560
G20: Amit | H20: 2448
G21: Ram Sales | H21: 2352
C22: Profit/Loss | G22: Grand Total | H22: 234960
C23: =C19+C15-C11 -> 33360
